odoo8_addon_hr_expense_sequence-8.0.1.0.0.99.dev12-nspkg.pth
odoo_addons/hr_expense_sequence/README.rst
odoo_addons/hr_expense_sequence/__init__.py
odoo_addons/hr_expense_sequence/__openerp__.py
odoo_addons/hr_expense_sequence/data/hr_expense_data.xml
odoo_addons/hr_expense_sequence/i18n/de.po
odoo_addons/hr_expense_sequence/i18n/es.po
odoo_addons/hr_expense_sequence/i18n/fi.po
odoo_addons/hr_expense_sequence/i18n/fr.po
odoo_addons/hr_expense_sequence/i18n/hr.po
odoo_addons/hr_expense_sequence/i18n/hr_expense_sequence.pot
odoo_addons/hr_expense_sequence/i18n/id.po
odoo_addons/hr_expense_sequence/i18n/it.po
odoo_addons/hr_expense_sequence/i18n/pt_BR.po
odoo_addons/hr_expense_sequence/i18n/pt_PT.po
odoo_addons/hr_expense_sequence/i18n/sl.po
odoo_addons/hr_expense_sequence/models/__init__.py
odoo_addons/hr_expense_sequence/models/hr_expense_expense.py
odoo_addons/hr_expense_sequence/static/description/icon.png
odoo_addons/hr_expense_sequence/views/hr_expense_expense_view.xml
odoo8_addon_hr_expense_sequence-8.0.1.0.0.99.dev12.dist-info/METADATA
odoo8_addon_hr_expense_sequence-8.0.1.0.0.99.dev12.dist-info/WHEEL
odoo8_addon_hr_expense_sequence-8.0.1.0.0.99.dev12.dist-info/namespace_packages.txt
odoo8_addon_hr_expense_sequence-8.0.1.0.0.99.dev12.dist-info/top_level.txt
odoo8_addon_hr_expense_sequence-8.0.1.0.0.99.dev12.dist-info/RECORD
